distiller/__init__.py
distiller/__main__.py
distiller/base.py
distiller/cli.py
distiller/conversations.py
distiller/outputs.py
distiller/texts.py
The_Distiller-0.0.2.dist-info/METADATA
The_Distiller-0.0.2.dist-info/WHEEL
The_Distiller-0.0.2.dist-info/entry_points.txt
The_Distiller-0.0.2.dist-info/top_level.txt
The_Distiller-0.0.2.dist-info/RECORD
