Metadata-Version: 2.1
Name: The-Distiller
Version: 0.0.2
Summary: Generate textual and conversational datasets with LLMs.
Home-page: https://github.com/kyegomez/The-Distiller
Author: Kye Gomez
Author-email: Kye@apac.ai
Keywords: dataset,llm,langchain,openai
Requires-Dist: langchain (>=0.0.113)
Requires-Dist: click (>=8.1)
